MANIFEST.in
README.txt
setup.py
ImageScales.egg-info/PKG-INFO
ImageScales.egg-info/SOURCES.txt
ImageScales.egg-info/dependency_links.txt
ImageScales.egg-info/entry_points.txt
ImageScales.egg-info/namespace_packages.txt
ImageScales.egg-info/not-zip-safe
ImageScales.egg-info/paster_plugins.txt
ImageScales.egg-info/requires.txt
ImageScales.egg-info/top_level.txt
Products/__init__.py
Products/ImageScales/__init__.py
Products/ImageScales/setuphandlers.py
Products/ImageScales/tests.py
Products/ImageScales/version.txt
docs/HISTORY.txt
docs/INSTALL.txt
docs/LICENSE.GPL
docs/LICENSE.txt