Metadata-Version: 1.0
Name: ImageScales
Version: 0.1
Summary: Patches ATImage to allows per site image scales.
Home-page: http://svn.plone.org/svn/collective/Products.ImageScales
Author: Steve McMahon
Author-email: steve@dcn.org
License: GPL
Keywords: web zope plone theme
Platform: UNKNOWN
Classifier: Framework :: Plone
Classifier: Programming Language :: Python
Classifier: Topic :: Software Development :: Libraries :: Python Modules
